fthat/__init__.py
fthat/ftpi.py
fthat-0.0.16.dist-info/METADATA
fthat-0.0.16.dist-info/WHEEL
fthat-0.0.16.dist-info/top_level.txt
fthat-0.0.16.dist-info/RECORD
